<?xml version="1.0" encoding="utf-8"?>
<GameData>
  <LocalizedText>
    <Replace Language='en_US' Tag="LOC_POLAND_JADWIGA_MOD_TITLE">
      <Text>DLC: Nền văn minh Poland - Ba Lan</Text>
    </Replace>
    <Replace Language='en_US' Tag="LOC_POLAND_JADWIGA_MOD_TEASER">
      <Text>Người lãnh đạo và nền văn minh mới - Jadwiga của Ba Lan</Text>
    </Replace>
    <Replace Language='en_US' Tag="LOC_POLAND_JADWIGA_MOD_DESCRIPTION">
      <Text>Chứa một nền văn minh và người lãnh đạo mới.</Text>
    </Replace>
    <Replace Language='en_US' Tag="LOC_MOD_POLAND_SCENARIO_TITLE">
      <Text>Kịch bản: Di sản của Jadwiga</Text>
    </Replace>
    <Replace Language='en_US' Tag="LOC_MOD_POLAND_SCENARIO_TEASER">
      <Text>Chiến đấu cùng với hai người chơi khác để bảo vệ Ba Lan khỏi giặc xâm lược.</Text>
    </Replace>
    <Replace Language='en_US' Tag="LOC_MOD_POLAND_SCENARIO_DESCRIPTION">
      <Text>Trong vòng 60 lượt kịch bản, đứng giữa trung tâm của châu Âu, bạn phải bảo vệ quê hương Ba Lan màu mỡ khỏi quân xâm lược liên tục từ nhiều hướng. Tập hợp Kỵ binh Winged Hussars của bạn đối mặt với Hiệp sĩ Teuton và đế quốc Kỳ Ottoman Thổ Nhĩ Kỳ cũng như phát triển nền văn minh.[NEWLINE][NEWLINE]Người chơi nào với đế chế có điểm số cao nhất vào cuối Game sẽ chiến thắng.</Text>
    </Replace>
  </LocalizedText>
</GameData>

